optprompt/__init__.py
optprompt/optprompt.py
optprompt-0.5.0.dist-info/METADATA
optprompt-0.5.0.dist-info/WHEEL
optprompt-0.5.0.dist-info/licenses/LICENSE
optprompt-0.5.0.dist-info/RECORD
