Metadata-Version: 2.3
Name: optprompt
Version: 0.5.0
Summary: A prompting option parser
Project-URL: Homepage, https://github.com/dstathis/optprompt
Project-URL: Bug Tracker, https://github.com/dstathis/optprompt/issues
Author-email: Dylan Stephano-Shachter <dylan@theone.ninja>
License-File: LICENSE
Classifier: Development Status :: 4 - Beta
Classifier: License :: OSI Approved :: GNU Affero General Public License v3
Classifier: Programming Language :: Python
Classifier: Topic :: Software Development :: Libraries :: Python Modules
Requires-Python: >=3.2
